<speak>
    <p ru="Плавать">
        <s meaning="word">Swim</s><break time="2000ms"/>
        <s meaning="example"></s><break time="1000ms"/>
    </p>
    <p ru="Мочь">
        <s meaning="word">Can</s><break time="2000ms"/>
        <s meaning="example"></s><break time="1000ms"/>
    </p>
    <p ru="Играть">
        <s meaning="word">Play</s><break time="2000ms"/>
        <s meaning="example"></s><break time="1000ms"/>
    </p>
    <p ru="Танцевать">
        <s meaning="word">Dance</s><break time="2000ms"/>
        <s meaning="example"></s><break time="1000ms"/>
    </p>
    <p ru="Ездить верхом">
        <s meaning="word">Ride</s><break time="2000ms"/>
        <s meaning="example"></s><break time="1000ms"/>
    </p>
    <p ru="Действовать">
        <s meaning="word">Activity</s><break time="2000ms"/>
        <s meaning="example"></s><break time="1000ms"/>
    </p>
    <p ru="">
        <s meaning="word"></s><break time="2000ms"/>
        <s meaning="example"></s><break time="1000ms"/>
    </p>
    <p ru="">
        <s meaning="word"></s><break time="2000ms"/>
        <s meaning="example"></s><break time="1000ms"/>
    </p>
</speak>
